dyngraphplot/__init__.py
dyngraphplot/dyngraphplot.py
dyngraphplot-1.2.2.dist-info/LICENSE
dyngraphplot-1.2.2.dist-info/METADATA
dyngraphplot-1.2.2.dist-info/WHEEL
dyngraphplot-1.2.2.dist-info/top_level.txt
dyngraphplot-1.2.2.dist-info/RECORD
