Metadata-Version: 2.1
Name: dyngraphplot
Version: 1.2.2
Summary: A module for plotting dynamic force-directed graphs
Home-page: https://github.com/tipech/dyngraphplot
Author: Tilemachos Pechlivanoglou
Author-email: tppehli@gmail.com
License: UNKNOWN
Platform: UNKNOWN
Classifier: Programming Language :: Python :: 3
Classifier: License :: OSI Approved :: MIT License
Classifier: Operating System :: OS Independent
